logging_basic_config/__init__.py
logging_basic_config/config.py
logging_basic_config-1.4.3.dist-info/LICENSE
logging_basic_config-1.4.3.dist-info/METADATA
logging_basic_config-1.4.3.dist-info/WHEEL
logging_basic_config-1.4.3.dist-info/top_level.txt
logging_basic_config-1.4.3.dist-info/RECORD
