Metadata-Version: 2.1
Name: logging-basic-config
Version: 1.4.3
Summary: Basic logging configurations to easily use in many projects
Home-page: https://github.com/msantino/logging-basic-config
Author: Marcelo Santino
Author-email: marcelo@santino.dev
Classifier: Programming Language :: Python :: 3
Classifier: License :: OSI Approved :: MIT License
Classifier: Operating System :: OS Independent
License-File: LICENSE
